{
  "name": "general-relevance-transform",
  "version": "0.1.0",
  "description": "Apply the General Relevance Transform to map domain structures and skill patterns across arbitrary contexts.",
  "category": "skill-engineering",
  "tags": [
    "transform",
    "skill",
    "analogy",
    "pattern"
  ],
  "dependencies": [],
  "relatedPlugins": [
    "skill-composer",
    "function-creator",
    "pattern-navigator"
  ],
  "tools": [
    "general_relevance_transform_guide"
  ],
  "entrypoint": "extension.mjs"
}
